README.txt
setup.cfg
setup.py
src/ClueBzrServer.egg-info/PKG-INFO
src/ClueBzrServer.egg-info/SOURCES.txt
src/ClueBzrServer.egg-info/dependency_links.txt
src/ClueBzrServer.egg-info/entry_points.txt
src/ClueBzrServer.egg-info/namespace_packages.txt
src/ClueBzrServer.egg-info/not-zip-safe
src/ClueBzrServer.egg-info/requires.txt
src/ClueBzrServer.egg-info/top_level.txt
src/clue/__init__.py
src/clue/bzrserver/__init__.py
src/clue/bzrserver/main.py
src/clue/bzrserver/server.py
src/clue/bzrserver/utils.py
src/clue/bzrserver/wsgi.py