Metadata-Version: 1.0
Name: ClueBzrServer
Version: 0.2
Summary: A standalone server application for serving up Bazaar repositories over HTTP
Home-page: http://projects.serverzen.com/pm/p/cluemapper/wiki/ClueBzrServer
Author: Rocky Burt
Author-email: rocky@serverzen.com
License: BSD
Keywords: bzr bazaar repoze.who dvcs
Platform: UNKNOWN
Classifier: Development Status :: 3 - Alpha
Classifier: Programming Language :: Python
Classifier: Topic :: Internet :: WWW/HTTP :: WSGI :: Application
Classifier: Topic :: Software Development :: Libraries :: Python Modules
Classifier: Topic :: Software Development :: Version Control
